setup.py
simplecaptcha/__init__.py
simplecaptcha/file.py
simplecaptcha/tests.py
simplecaptcha/words.py
simplecaptcha.egg-info/PKG-INFO
simplecaptcha.egg-info/SOURCES.txt
simplecaptcha.egg-info/dependency_links.txt
simplecaptcha.egg-info/requires.txt
simplecaptcha.egg-info/top_level.txt
simplecaptcha/visual/__init__.py
simplecaptcha/visual/backgrounds.py
simplecaptcha/visual/distortions.py
simplecaptcha/visual/pictures.py
simplecaptcha/visual/tests.py
simplecaptcha/visual/text.py