Metadata-Version: 1.0
Name: simplecaptcha
Version: 0.5
Summary: A Python framework for CAPTCHA tests
Home-page: UNKNOWN
Author: Isaac Cook
Author-email: isaac@simpload.com
License: MIT
Platform: UNKNOWN
